./.gitignore
./LICENSE
./MCP-Kali-Server_process.log
./PKG-INFO
./README.md
./kali_server.py
./mcp_server.py
./pyproject.toml
./requirements.txt
iflow_mcp_mcp_kali_server-0.1.0.dist-info/METADATA
iflow_mcp_mcp_kali_server-0.1.0.dist-info/WHEEL
iflow_mcp_mcp_kali_server-0.1.0.dist-info/entry_points.txt
iflow_mcp_mcp_kali_server-0.1.0.dist-info/licenses/LICENSE
iflow_mcp_mcp_kali_server-0.1.0.dist-info/RECORD
