Metadata-Version: 2.4
Name: iflow-mcp_MCP-Kali-Server
Version: 0.1.0
Summary: MCP server for Kali Linux security tools integration
Author-email: IFLOW <iflow@example.com>
License: MIT
License-File: LICENSE
Requires-Python: >=3.8
Requires-Dist: mcp>=1.0.0
Requires-Dist: requests>=2.31.0
